django_sqlite_tenants/__init__.py
django_sqlite_tenants/admin_sites.py
django_sqlite_tenants/apps.py
django_sqlite_tenants/cache.py
django_sqlite_tenants/conf.py
django_sqlite_tenants/context_processors.py
django_sqlite_tenants/db_routers.py
django_sqlite_tenants/enums.py
django_sqlite_tenants/log.py
django_sqlite_tenants/middlewares.py
django_sqlite_tenants/models.py
django_sqlite_tenants/settings_example.py
django_sqlite_tenants/settings_verify.py
django_sqlite_tenants/signals.py
django_sqlite_tenants/storages.py
django_sqlite_tenants/tests.py
django_sqlite_tenants/utils.py
django_sqlite_tenants/admin/app_list.html
django_sqlite_tenants/admin/index.html
django_sqlite_tenants/admin/django_sqlite_tenants/tenant/change_form.html
django_sqlite_tenants/management/__init__.py
django_sqlite_tenants/management/commands/__init__.py
django_sqlite_tenants/management/commands/create_tenant.py
django_sqlite_tenants/management/commands/migrate_tenant.py
django_sqlite_tenants-0.1.0.dist-info/METADATA
django_sqlite_tenants-0.1.0.dist-info/WHEEL
django_sqlite_tenants-0.1.0.dist-info/RECORD
