Metadata-Version: 2.4
Name: django-sqlite-tenants
Version: 0.1.0
Summary: Sqlite Based Multi Tenancy With Django
Requires-Python: >=3.13
Requires-Dist: django>=5.2.0
